{
  "archetypeId": "rainbow_connected",
  "boardsAnalyzed": 24,
  "ip_facing_bet": {
    "two_pair": {
      "fold": 0.3174,
      "call": 0.4765,
      "raise": 0.2061,
      "count": 5517
    },
    "air": {
      "fold": 0.9482,
      "call": 0.0305,
      "raise": 0.0213,
      "count": 1788
    },
    "straight_draw": {
      "fold": 0.2374,
      "call": 0.4242,
      "raise": 0.3384,
      "count": 5664
    },
    "overcards": {
      "fold": 0.6185,
      "call": 0.3232,
      "raise": 0.0584,
      "count": 14640
    },
    "middle_pair": {
      "fold": 0.2812,
      "call": 0.6536,
      "raise": 0.0652,
      "count": 2448
    },
    "top_pair_top_kicker": {
      "fold": 0.2267,
      "call": 0.56,
      "raise": 0.2133,
      "count": 1710
    },
    "bottom_pair": {
      "fold": 0.3532,
      "call": 0.5954,
      "raise": 0.0514,
      "count": 2187
    },
    "sets_plus": {
      "fold": 0.0344,
      "call": 0.5238,
      "raise": 0.4418,
      "count": 648
    },
    "top_pair_weak_kicker": {
      "fold": 0.2209,
      "call": 0.5476,
      "raise": 0.2314,
      "count": 1161
    }
  },
  "oop_facing_bet": {
    "two_pair": {
      "fold": 0.2872,
      "call": 0.476,
      "raise": 0.2368,
      "count": 5823
    },
    "air": {
      "fold": 0.9948,
      "call": 0.0052,
      "raise": 0,
      "count": 3792
    },
    "straight_draw": {
      "fold": 0.2807,
      "call": 0.3835,
      "raise": 0.3358,
      "count": 8232
    },
    "overcards": {
      "fold": 0.6897,
      "call": 0.2742,
      "raise": 0.0361,
      "count": 17688
    },
    "middle_pair": {
      "fold": 0.3109,
      "call": 0.5944,
      "raise": 0.0947,
      "count": 3348
    },
    "top_pair_top_kicker": {
      "fold": 0.2549,
      "call": 0.5977,
      "raise": 0.1474,
      "count": 1800
    },
    "bottom_pair": {
      "fold": 0.3716,
      "call": 0.5602,
      "raise": 0.0682,
      "count": 3258
    },
    "sets_plus": {
      "fold": 0.0265,
      "call": 0.5287,
      "raise": 0.4448,
      "count": 648
    },
    "top_pair_weak_kicker": {
      "fold": 0.248,
      "call": 0.4618,
      "raise": 0.2902,
      "count": 2295
    }
  }
}