{
  "22": 0.222,
  "33": 0.241,
  "44": 0.264,
  "55": 0.289,
  "66": 0.315,
  "77": 0.346,
  "88": 0.377,
  "99": 0.411,
  "AA": 0.641,
  "AKs": 0.416,
  "AQs": 0.398,
  "AJs": 0.386,
  "ATs": 0.372,
  "A9s": 0.348,
  "A8s": 0.334,
  "A7s": 0.324,
  "A6s": 0.315,
  "A5s": 0.319,
  "A4s": 0.314,
  "A3s": 0.306,
  "A2s": 0.297,
  "AKo": 0.386,
  "KK": 0.582,
  "KQs": 0.381,
  "KJs": 0.37,
  "KTs": 0.358,
  "K9s": 0.33,
  "K8s": 0.307,
  "K7s": 0.3,
  "K6s": 0.29,
  "K5s": 0.282,
  "K4s": 0.278,
  "K3s": 0.27,
  "K2s": 0.265,
  "AQo": 0.366,
  "KQo": 0.353,
  "QQ": 0.536,
  "QJs": 0.356,
  "QTs": 0.347,
  "Q9s": 0.318,
  "Q8s": 0.296,
  "Q7s": 0.278,
  "Q6s": 0.271,
  "Q5s": 0.263,
  "Q4s": 0.257,
  "Q3s": 0.252,
  "Q2s": 0.247,
  "AJo": 0.353,
  "KJo": 0.336,
  "QJo": 0.328,
  "JJ": 0.491,
  "JTs": 0.342,
  "J9s": 0.312,
  "J8s": 0.291,
  "J7s": 0.273,
  "J6s": 0.254,
  "J5s": 0.247,
  "J4s": 0.242,
  "J3s": 0.235,
  "J2s": 0.228,
  "ATo": 0.341,
  "KTo": 0.326,
  "QTo": 0.313,
  "JTo": 0.304,
  "TT": 0.454,
  "T9s": 0.309,
  "T8s": 0.29,
  "T7s": 0.269,
  "T6s": 0.253,
  "T5s": 0.236,
  "T4s": 0.227,
  "T3s": 0.223,
  "T2s": 0.216,
  "A9o": 0.311,
  "K9o": 0.298,
  "Q9o": 0.285,
  "J9o": 0.279,
  "T9o": 0.279,
  "98s": 0.285,
  "97s": 0.268,
  "96s": 0.252,
  "95s": 0.23,
  "94s": 0.216,
  "93s": 0.21,
  "92s": 0.205,
  "A8o": 0.303,
  "K8o": 0.273,
  "Q8o": 0.262,
  "J8o": 0.256,
  "T8o": 0.255,
  "98o": 0.251,
  "87s": 0.267,
  "86s": 0.251,
  "85s": 0.232,
  "84s": 0.215,
  "83s": 0.199,
  "82s": 0.194,
  "A7o": 0.289,
  "K7o": 0.264,
  "Q7o": 0.243,
  "J7o": 0.234,
  "T7o": 0.235,
  "97o": 0.232,
  "87o": 0.234,
  "76s": 0.254,
  "75s": 0.237,
  "74s": 0.22,
  "73s": 0.202,
  "72s": 0.188,
  "A6o": 0.278,
  "K6o": 0.252,
  "Q6o": 0.233,
  "J6o": 0.213,
  "T6o": 0.213,
  "96o": 0.215,
  "86o": 0.215,
  "76o": 0.216,
  "65s": 0.239,
  "64s": 0.224,
  "63s": 0.208,
  "62s": 0.189,
  "A5o": 0.28,
  "K5o": 0.248,
  "Q5o": 0.225,
  "J5o": 0.21,
  "T5o": 0.195,
  "95o": 0.194,
  "85o": 0.198,
  "75o": 0.2,
  "65o": 0.202,
  "54s": 0.231,
  "53s": 0.214,
  "52s": 0.197,
  "A4o": 0.272,
  "K4o": 0.238,
  "Q4o": 0.214,
  "J4o": 0.201,
  "T4o": 0.187,
  "94o": 0.177,
  "84o": 0.175,
  "74o": 0.179,
  "64o": 0.185,
  "54o": 0.191,
  "43s": 0.207,
  "42s": 0.19,
  "A3o": 0.261,
  "K3o": 0.231,
  "Q3o": 0.208,
  "J3o": 0.193,
  "T3o": 0.182,
  "93o": 0.169,
  "83o": 0.159,
  "73o": 0.161,
  "63o": 0.167,
  "53o": 0.175,
  "43o": 0.166,
  "32s": 0.182,
  "A2o": 0.253,
  "K2o": 0.226,
  "Q2o": 0.206,
  "J2o": 0.186,
  "T2o": 0.175,
  "92o": 0.162,
  "82o": 0.153,
  "72o": 0.144,
  "62o": 0.149,
  "52o": 0.156,
  "42o": 0.152,
  "32o": 0.142
}
